pinkpig/Mypy.py
pinkpig/__init__.py
pinkpig-1.1.1.dist-info/LICENSE
pinkpig-1.1.1.dist-info/METADATA
pinkpig-1.1.1.dist-info/WHEEL
pinkpig-1.1.1.dist-info/top_level.txt
pinkpig-1.1.1.dist-info/RECORD
